README.md
setup.py
ediri_azapi/__init__.py
ediri_azapi/_inputs.py
ediri_azapi/_utilities.py
ediri_azapi/data_plane_resource.py
ediri_azapi/get_resource.py
ediri_azapi/get_resource_action.py
ediri_azapi/get_resource_id.py
ediri_azapi/get_resource_list.py
ediri_azapi/outputs.py
ediri_azapi/provider.py
ediri_azapi/pulumi-plugin.json
ediri_azapi/py.typed
ediri_azapi/resource.py
ediri_azapi/resource_action.py
ediri_azapi/update_resource.py
ediri_azapi.egg-info/PKG-INFO
ediri_azapi.egg-info/SOURCES.txt
ediri_azapi.egg-info/dependency_links.txt
ediri_azapi.egg-info/not-zip-safe
ediri_azapi.egg-info/requires.txt
ediri_azapi.egg-info/top_level.txt
ediri_azapi/config/__init__.py
ediri_azapi/config/outputs.py
ediri_azapi/config/vars.py