Metadata-Version: 2.1
Name: ediri-azapi
Version: 1.12.1
Summary: A Pulumi package for creating and managing Azapi resources
Home-page: https://github.com/dirien/pulumi-azapi
License: Apache-2.0
Project-URL: Repository, https://github.com/dirien/pulumi-azapi
Keywords: pulumi azapi category/cloud
Platform: UNKNOWN
Requires-Python: >=3.8
